mongodb_connect/__init__.py
mongodb_connect/mongo_crud.py
pipeline/__init__.py
pipeline/predicition_pipeline.py
pipeline/training_pipeline.py
utils/__init__.py
utils/utils.py
mongodbConnector_pZero-0.0.4.dist-info/LICENSE
mongodbConnector_pZero-0.0.4.dist-info/METADATA
mongodbConnector_pZero-0.0.4.dist-info/WHEEL
mongodbConnector_pZero-0.0.4.dist-info/top_level.txt
mongodbConnector_pZero-0.0.4.dist-info/RECORD
